Metadata-Version: 2.1
Name: justanunsuspiciousmodule
Version: 1.0
Summary: Class with a module for lab
Home-page: https://github.com/Igor-Sviridov/justanunsuspiciousmodule
Author: Mekatto
Author-email: igor@mekatto.com
License: MIT
Download-URL: https://pypi.org/project/justanunsuspiciousmodule/
Platform: UNKNOWN
Requires-Python: >3.6.0
License-File: LICENSE
